microarchiver/__init__.py
microarchiver/__main__.py
microarchiver/exceptions.py
microarchiver/files.py
microarchiver/network.py
microarchiver/data/JATS-Archiving-1-2-MathML3-DTD/BITS-embedded-index2.ent
microarchiver/data/JATS-Archiving-1-2-MathML3-DTD/JATS-XHTMLtablesetup1.ent
microarchiver/data/JATS-Archiving-1-2-MathML3-DTD/JATS-ali-namespace1.ent
microarchiver/data/JATS-Archiving-1-2-MathML3-DTD/JATS-archivearticle1-mathml3.dtd
microarchiver/data/JATS-Archiving-1-2-MathML3-DTD/JATS-archivecustom-classes1.ent
microarchiver/data/JATS-Archiving-1-2-MathML3-DTD/JATS-archivecustom-mixes1.ent
microarchiver/data/JATS-Archiving-1-2-MathML3-DTD/JATS-archivecustom-models1.ent
microarchiver/data/JATS-Archiving-1-2-MathML3-DTD/JATS-archivecustom-modules1.ent
microarchiver/data/JATS-Archiving-1-2-MathML3-DTD/JATS-articlemeta1.ent
microarchiver/data/JATS-Archiving-1-2-MathML3-DTD/JATS-backmatter1.ent
microarchiver/data/JATS-Archiving-1-2-MathML3-DTD/JATS-chars1.ent
microarchiver/data/JATS-Archiving-1-2-MathML3-DTD/JATS-common-atts1.ent
microarchiver/data/JATS-Archiving-1-2-MathML3-DTD/JATS-common1.ent
microarchiver/data/JATS-Archiving-1-2-MathML3-DTD/JATS-default-classes1.ent
microarchiver/data/JATS-Archiving-1-2-MathML3-DTD/JATS-default-mixes1.ent
microarchiver/data/JATS-Archiving-1-2-MathML3-DTD/JATS-display1.ent
microarchiver/data/JATS-Archiving-1-2-MathML3-DTD/JATS-format1.ent
microarchiver/data/JATS-Archiving-1-2-MathML3-DTD/JATS-funding1.ent
microarchiver/data/JATS-Archiving-1-2-MathML3-DTD/JATS-journalmeta1.ent
microarchiver/data/JATS-Archiving-1-2-MathML3-DTD/JATS-link1.ent
microarchiver/data/JATS-Archiving-1-2-MathML3-DTD/JATS-list1.ent
microarchiver/data/JATS-Archiving-1-2-MathML3-DTD/JATS-math1.ent
microarchiver/data/JATS-Archiving-1-2-MathML3-DTD/JATS-mathml3-mathmlsetup1.ent
microarchiver/data/JATS-Archiving-1-2-MathML3-DTD/JATS-mathml3-modules1.ent
microarchiver/data/JATS-Archiving-1-2-MathML3-DTD/JATS-modules1.ent
microarchiver-1.12.1.dist-info/LICENSE
microarchiver-1.12.1.dist-info/METADATA
microarchiver-1.12.1.dist-info/WHEEL
microarchiver-1.12.1.dist-info/top_level.txt
microarchiver-1.12.1.dist-info/RECORD
