Metadata-Version: 2.1
Name: microarchiver
Version: 1.12.1
Summary: Archives articles from microPublication.org
Home-page: https://github.com/caltechlibrary/microarchiver
Author: Michael Hucka, Tom Morrell
Author-email: mhucka@caltech.edu, tmorrell@library.caltech.edu
License: BSD 3-clause
Project-URL: Source Code, https://github.com/caltechlibrary/microarchiver
Project-URL: Bug Tracker, https://github.com/caltechlibrary/microarchiver/issues
Keywords: journal publishing,archiving
Platform: UNKNOWN
Classifier: Development Status :: 5 - Production/Stable
Classifier: Environment :: Console
Classifier: Intended Audience :: Science/Research
Classifier: License :: OSI Approved :: BSD License
Classifier: Operating System :: MacOS :: MacOS X
Classifier: Operating System :: Microsoft :: Windows
Classifier: Operating System :: POSIX
Classifier: Operating System :: POSIX :: Linux
Classifier: Operating System :: Unix
Classifier: Programming Language :: Python
Classifier: Programming Language :: Python :: 3.5
Classifier: Topic :: System :: Archiving
Classifier: Topic :: System :: Archiving :: Packaging
Classifier: Topic :: Utilities
Requires-Python: >=3.5
Requires-Dist: colorful (>=0.5.1)
Requires-Dist: commonpy (>=1.3.4)
Requires-Dist: dateparser (>=0.7.0)
Requires-Dist: humanize (>=0.5.1)
Requires-Dist: lxml (>=4.2.5)
Requires-Dist: Pillow (>=5.2.0)
Requires-Dist: plac (>=1.0.0)
Requires-Dist: pypubsub (>=4.0.0)
Requires-Dist: python-dateutil (>=2.8.1)
Requires-Dist: recordclass (>=0.11.1)
Requires-Dist: requests (>=2.21.0)
Requires-Dist: setuptools (>=40.0.0)
Requires-Dist: sidetrack (>=1.2.0)
Requires-Dist: urllib3 (>=1.24.1)
Requires-Dist: xmltodict (>=0.12.0)
